codestarter/__init__.py
codestarter/cli.py
codestarter/executor.py
codestarter/utils.py
codestarter/dependency_resolvers/__init__.py
codestarter/dependency_resolvers/requirements_resolver.py
codestarter/dependency_resolvers/utils.py
codestarter/file/__init__.py
codestarter/file/local.py
codestarter/file/utils.py
codestarter-0.0.1.dist-info/METADATA
codestarter-0.0.1.dist-info/WHEEL
codestarter-0.0.1.dist-info/entry_points.txt
codestarter-0.0.1.dist-info/licenses/LICENSE
codestarter-0.0.1.dist-info/RECORD
