Metadata-Version: 2.3
Name: codestarter
Version: 0.0.1
Summary: A tool for assembling a repo using copy/paste
Project-URL: Homepage, https://github.com/pateli18/codestarter
Project-URL: Issues, https://github.com/pateli18/codestarter/issues
Author: Ihsaan Patel
License-File: LICENSE
Classifier: License :: OSI Approved :: Apache Software License
Classifier: Operating System :: OS Independent
Classifier: Programming Language :: Python :: 3
Requires-Python: >=3.10
Requires-Dist: pydantic
Requires-Dist: pydantic-settings
Provides-Extra: cli
Requires-Dist: typer; extra == 'cli'
Provides-Extra: local
Requires-Dist: aiofiles; extra == 'local'
Provides-Extra: pythondep
Requires-Dist: packaging; extra == 'pythondep'
